syntactes/__init__.py
syntactes/_action.py
syntactes/_item.py
syntactes/_state.py
syntactes/generator.py
syntactes/grammar.py
syntactes/rule.py
syntactes/token.py
syntactes/parser/__init__.py
syntactes/parser/exception.py
syntactes/parser/execute.py
syntactes/parser/parser.py
syntactes/parsing_table/__init__.py
syntactes/parsing_table/conflict.py
syntactes/parsing_table/entry.py
syntactes/parsing_table/table.py
syntactes-0.4.0.dist-info/LICENSE
syntactes-0.4.0.dist-info/METADATA
syntactes-0.4.0.dist-info/WHEEL
syntactes-0.4.0.dist-info/top_level.txt
syntactes-0.4.0.dist-info/RECORD
